{
  "attributes": [
    {
      "allow_nil?": false,
      "default": "fragment(\"uuidv7()\")",
      "generated?": true,
      "precision": null,
      "primary_key?": true,
      "references": null,
      "scale": null,
      "size": null,
      "source": "id",
      "type": "uuid"
    },
    {
      "allow_nil?": false,
      "default": "nil",
      "generated?": false,
      "precision": null,
      "primary_key?": false,
      "references": null,
      "scale": null,
      "size": null,
      "source": "event_type",
      "type": "text"
    },
    {
      "allow_nil?": false,
      "default": "nil",
      "generated?": false,
      "precision": null,
      "primary_key?": false,
      "references": null,
      "scale": null,
      "size": null,
      "source": "version",
      "type": "bigint"
    },
    {
      "allow_nil?": false,
      "default": "nil",
      "generated?": false,
      "precision": null,
      "primary_key?": false,
      "references": null,
      "scale": null,
      "size": null,
      "source": "event_key",
      "type": "text"
    },
    {
      "allow_nil?": true,
      "default": "nil",
      "generated?": false,
      "precision": null,
      "primary_key?": false,
      "references": null,
      "scale": null,
      "size": null,
      "source": "delivery",
      "type": "map"
    },
    {
      "allow_nil?": true,
      "default": "nil",
      "generated?": false,
      "precision": null,
      "primary_key?": false,
      "references": null,
      "scale": null,
      "size": null,
      "source": "body_hash",
      "type": "text"
    },
    {
      "allow_nil?": false,
      "default": "\"pending\"",
      "generated?": false,
      "precision": null,
      "primary_key?": false,
      "references": null,
      "scale": null,
      "size": null,
      "source": "state",
      "type": "text"
    },
    {
      "allow_nil?": false,
      "default": "0",
      "generated?": false,
      "precision": null,
      "primary_key?": false,
      "references": null,
      "scale": null,
      "size": null,
      "source": "attempts",
      "type": "bigint"
    },
    {
      "allow_nil?": true,
      "default": "nil",
      "generated?": false,
      "precision": null,
      "primary_key?": false,
      "references": null,
      "scale": null,
      "size": null,
      "source": "last_error",
      "type": "text"
    },
    {
      "allow_nil?": true,
      "default": "nil",
      "generated?": false,
      "precision": null,
      "primary_key?": false,
      "references": null,
      "scale": null,
      "size": null,
      "source": "delivery_metadata",
      "type": "map"
    },
    {
      "allow_nil?": true,
      "default": "nil",
      "generated?": false,
      "precision": null,
      "primary_key?": false,
      "references": null,
      "scale": null,
      "size": null,
      "source": "claimed_at",
      "type": "utc_datetime_usec"
    },
    {
      "allow_nil?": true,
      "default": "nil",
      "generated?": false,
      "precision": null,
      "primary_key?": false,
      "references": null,
      "scale": null,
      "size": null,
      "source": "next_attempt_at",
      "type": "utc_datetime_usec"
    },
    {
      "allow_nil?": true,
      "default": "nil",
      "generated?": false,
      "precision": null,
      "primary_key?": false,
      "references": null,
      "scale": null,
      "size": null,
      "source": "terminal_reason",
      "type": "text"
    },
    {
      "allow_nil?": true,
      "default": "nil",
      "generated?": false,
      "precision": null,
      "primary_key?": false,
      "references": null,
      "scale": null,
      "size": null,
      "source": "delivered_at",
      "type": "utc_datetime_usec"
    },
    {
      "allow_nil?": false,
      "default": "fragment(\"(now() AT TIME ZONE 'utc')\")",
      "generated?": false,
      "precision": null,
      "primary_key?": false,
      "references": null,
      "scale": null,
      "size": null,
      "source": "created_at",
      "type": "utc_datetime_usec"
    },
    {
      "allow_nil?": false,
      "default": "fragment(\"(now() AT TIME ZONE 'utc')\")",
      "generated?": false,
      "precision": null,
      "primary_key?": false,
      "references": null,
      "scale": null,
      "size": null,
      "source": "updated_at",
      "type": "utc_datetime_usec"
    },
    {
      "allow_nil?": false,
      "default": "nil",
      "generated?": false,
      "precision": null,
      "primary_key?": false,
      "references": {
        "deferrable": false,
        "destination_attribute": "id",
        "destination_attribute_default": null,
        "destination_attribute_generated": null,
        "index?": false,
        "match_type": null,
        "match_with": null,
        "multitenancy": {
          "attribute": null,
          "global": null,
          "strategy": null
        },
        "name": "outbound_event_deliveries_event_id_fkey",
        "on_delete": "delete",
        "on_update": "restrict",
        "primary_key?": true,
        "schema": "public",
        "table": "outbound_events"
      },
      "scale": null,
      "size": null,
      "source": "event_id",
      "type": "uuid"
    },
    {
      "allow_nil?": false,
      "default": "nil",
      "generated?": false,
      "precision": null,
      "primary_key?": false,
      "references": {
        "deferrable": false,
        "destination_attribute": "id",
        "destination_attribute_default": null,
        "destination_attribute_generated": null,
        "index?": false,
        "match_type": null,
        "match_with": null,
        "multitenancy": {
          "attribute": null,
          "global": null,
          "strategy": null
        },
        "name": "outbound_event_deliveries_subscription_id_fkey",
        "on_delete": "delete",
        "on_update": "restrict",
        "primary_key?": true,
        "schema": "public",
        "table": "outbound_subscriptions"
      },
      "scale": null,
      "size": null,
      "source": "subscription_id",
      "type": "uuid"
    },
    {
      "allow_nil?": false,
      "default": "nil",
      "generated?": false,
      "precision": null,
      "primary_key?": false,
      "references": {
        "deferrable": false,
        "destination_attribute": "id",
        "destination_attribute_default": null,
        "destination_attribute_generated": null,
        "index?": false,
        "match_type": null,
        "match_with": null,
        "multitenancy": {
          "attribute": null,
          "global": null,
          "strategy": null
        },
        "name": "outbound_event_deliveries_connection_id_fkey",
        "on_delete": "delete",
        "on_update": "restrict",
        "primary_key?": true,
        "schema": "public",
        "table": "outbound_connections"
      },
      "scale": null,
      "size": null,
      "source": "connection_id",
      "type": "uuid"
    }
  ],
  "base_filter": null,
  "check_constraints": [],
  "create_table_options": null,
  "custom_indexes": [
    {
      "all_tenants?": false,
      "concurrently": false,
      "error_fields": [
        "event_id"
      ],
      "fields": [
        {
          "type": "atom",
          "value": "event_id"
        }
      ],
      "include": null,
      "message": null,
      "name": null,
      "nulls_distinct": true,
      "prefix": null,
      "table": null,
      "unique": false,
      "using": null,
      "where": null
    },
    {
      "all_tenants?": false,
      "concurrently": false,
      "error_fields": [
        "subscription_id",
        "state"
      ],
      "fields": [
        {
          "type": "atom",
          "value": "subscription_id"
        },
        {
          "type": "atom",
          "value": "state"
        }
      ],
      "include": null,
      "message": null,
      "name": null,
      "nulls_distinct": true,
      "prefix": null,
      "table": null,
      "unique": false,
      "using": null,
      "where": null
    },
    {
      "all_tenants?": false,
      "concurrently": false,
      "error_fields": [
        "connection_id",
        "event_key",
        "state"
      ],
      "fields": [
        {
          "type": "atom",
          "value": "connection_id"
        },
        {
          "type": "atom",
          "value": "event_key"
        },
        {
          "type": "atom",
          "value": "state"
        }
      ],
      "include": null,
      "message": null,
      "name": null,
      "nulls_distinct": true,
      "prefix": null,
      "table": null,
      "unique": false,
      "using": null,
      "where": null
    },
    {
      "all_tenants?": false,
      "concurrently": false,
      "error_fields": [
        "subscription_id",
        "event_key",
        "state"
      ],
      "fields": [
        {
          "type": "atom",
          "value": "subscription_id"
        },
        {
          "type": "atom",
          "value": "event_key"
        },
        {
          "type": "atom",
          "value": "state"
        }
      ],
      "include": null,
      "message": null,
      "name": null,
      "nulls_distinct": true,
      "prefix": null,
      "table": null,
      "unique": false,
      "using": null,
      "where": null
    },
    {
      "all_tenants?": false,
      "concurrently": false,
      "error_fields": [
        "state",
        "updated_at"
      ],
      "fields": [
        {
          "type": "atom",
          "value": "state"
        },
        {
          "type": "atom",
          "value": "updated_at"
        }
      ],
      "include": null,
      "message": null,
      "name": null,
      "nulls_distinct": true,
      "prefix": null,
      "table": null,
      "unique": false,
      "using": null,
      "where": null
    },
    {
      "all_tenants?": false,
      "concurrently": false,
      "error_fields": [
        "connection_id"
      ],
      "fields": [
        {
          "type": "atom",
          "value": "connection_id"
        }
      ],
      "include": null,
      "message": null,
      "name": null,
      "nulls_distinct": true,
      "prefix": null,
      "table": null,
      "unique": false,
      "using": null,
      "where": null
    },
    {
      "all_tenants?": false,
      "concurrently": false,
      "error_fields": [
        "connection_id",
        "event_key"
      ],
      "fields": [
        {
          "type": "atom",
          "value": "connection_id"
        },
        {
          "type": "atom",
          "value": "event_key"
        }
      ],
      "include": null,
      "message": null,
      "name": "idx_one_scheduled_per_connection_event_key",
      "nulls_distinct": true,
      "prefix": null,
      "table": null,
      "unique": true,
      "using": null,
      "where": "state IN ('scheduled', 'failed')"
    },
    {
      "all_tenants?": false,
      "concurrently": false,
      "error_fields": [
        "connection_id",
        "event_key",
        "event_id"
      ],
      "fields": [
        {
          "type": "atom",
          "value": "connection_id"
        },
        {
          "type": "atom",
          "value": "event_key"
        },
        {
          "type": "atom",
          "value": "event_id"
        }
      ],
      "include": null,
      "message": null,
      "name": "idx_event_deliveries_schedulable_lane",
      "nulls_distinct": true,
      "prefix": null,
      "table": null,
      "unique": false,
      "using": null,
      "where": "state IN ('pending', 'parked', 'failed')"
    },
    {
      "all_tenants?": false,
      "concurrently": false,
      "error_fields": [
        "connection_id",
        "event_id"
      ],
      "fields": [
        {
          "type": "atom",
          "value": "connection_id"
        },
        {
          "type": "atom",
          "value": "event_id"
        }
      ],
      "include": null,
      "message": null,
      "name": "idx_event_deliveries_delivery_claim",
      "nulls_distinct": true,
      "prefix": null,
      "table": null,
      "unique": false,
      "using": null,
      "where": "state = 'scheduled'"
    },
    {
      "all_tenants?": false,
      "concurrently": false,
      "error_fields": [
        "subscription_id",
        "event_key",
        "event_id"
      ],
      "fields": [
        {
          "type": "atom",
          "value": "subscription_id"
        },
        {
          "type": "atom",
          "value": "event_key"
        },
        {
          "type": "atom",
          "value": "event_id"
        }
      ],
      "include": [
        "body_hash"
      ],
      "message": null,
      "name": "idx_event_deliveries_dedup_baseline",
      "nulls_distinct": true,
      "prefix": null,
      "table": null,
      "unique": false,
      "using": null,
      "where": "state = 'delivered'"
    }
  ],
  "custom_statements": [],
  "has_create_action": true,
  "hash": "71AC236F25E1CE62D814C4E08DE0415B1DD255D24D037E9446800690AB0CBA4B",
  "identities": [
    {
      "all_tenants?": false,
      "base_filter": null,
      "index_name": "outbound_event_deliveries_unique_event_subscription_index",
      "keys": [
        {
          "type": "atom",
          "value": "event_id"
        },
        {
          "type": "atom",
          "value": "subscription_id"
        }
      ],
      "name": "unique_event_subscription",
      "nils_distinct?": true,
      "where": null
    }
  ],
  "multitenancy": {
    "attribute": null,
    "global": null,
    "strategy": null
  },
  "repo": "Elixir.Example.Repo",
  "schema": null,
  "table": "outbound_event_deliveries"
}